pydisper96_.cpython-313-x86_64-linux-gnu.so
pydisper96/__init__.py
pydisper96/disper96.py
pydisper96-1.2.4.data/scripts/disper96
pydisper96-1.2.4.dist-info/licenses/LICENSE.md
pydisper96-1.2.4.dist-info/METADATA
pydisper96-1.2.4.dist-info/WHEEL
pydisper96-1.2.4.dist-info/top_level.txt
pydisper96-1.2.4.dist-info/RECORD
