Metadata-Version: 2.4
Name: pydisper96
Version: 1.2.4
Summary: Python binding to BSD C port of Herrmann's srfdis96.
Home-page: 
License: BSD-3-clause
Classifier: Programming Language :: Python :: 3
Classifier: Topic :: Scientific/Engineering :: Physics
License-File: LICENSE.md
Requires-Dist: py3toolset
Requires-Dist: numpy
Dynamic: classifier
Dynamic: license
Dynamic: license-file
Dynamic: requires-dist
Dynamic: summary
